crams_provision/__init__.py
crams_provision/asgi.py
crams_provision/settings.py
crams_provision/test_utils.py
crams_provision/urls.py
crams_provision/utils.py
crams_provision/views.py
crams_provision/wsgi.py
crams_provision/config/__init__.py
crams_provision/config/provision_config.py
crams_provision/log/__init__.py
crams_provision/log/provision_log.py
crams_provision/serializers/__init__.py
crams_provision/serializers/base.py
crams_provision/serializers/product_provision.py
crams_provision/serializers/projectid_contact_provision.py
crams_provision/serializers/user_id_provision.py
crams_provision/serializers/manual_provision/__init__.py
crams_provision/serializers/manual_provision/product_provision.py
crams_provision/serializers/manual_provision/provision_details.py
crams_provision/serializers/manual_provision/provision_serializers.py
crams_provision/utils/__init__.py
crams_provision/utils/base.py
crams_provision/utils/product_utils.py
crams_provision/utils/provision_utils.py
crams_provision/utils/storage_product_provision_id.py
crams_provision/views/__init__.py
crams_provision/views/provision_request_list.py
crams_provision/viewsets/__init__.py
crams_provision/viewsets/allocation_provision.py
crams_provision/viewsets/base.py
crams_provision/viewsets/contact_id_provision.py
crams_provision/viewsets/manual_project_request_provision.py
crams_provision/viewsets/project_id_provision.py
crams_provision/viewsets/provision_request.py
crams_provision-1.0.1.7.dist-info/METADATA
crams_provision-1.0.1.7.dist-info/WHEEL
crams_provision-1.0.1.7.dist-info/top_level.txt
crams_provision-1.0.1.7.dist-info/RECORD
